sucrose/__init__.py
sucrose_ollama-0.1.1.dist-info/METADATA
sucrose_ollama-0.1.1.dist-info/WHEEL
sucrose_ollama-0.1.1.dist-info/licenses/LICENSE
sucrose_ollama-0.1.1.dist-info/RECORD
