Metadata-Version: 2.3
Name: sucrose_ollama
Version: 0.1.1
Summary: Add your description here
Author-email: Paul English <paulnglsh@gmail.com>
License-File: LICENSE
Requires-Python: >=3.8
Requires-Dist: ollama>=0.3.1
